cougar/__init__.py
cougar/rolling.cp311-win_amd64.pyd
cougar/numpy/__init__.py
cougar/numpy/functional.py
cougar/pandas/__init__.py
cougar-0.5.13.dist-info/LICENSE
cougar-0.5.13.dist-info/METADATA
cougar-0.5.13.dist-info/WHEEL
cougar-0.5.13.dist-info/top_level.txt
cougar-0.5.13.dist-info/RECORD
